LICENSE
MANIFEST.in
README.md
setup.cfg
setup.py
docs/Makefile
docs/conf.py
docs/index.rst
docs/make.bat
docs/options.rst
docs/quickstart.rst
docs/_static/authorization_area.png
docs/_static/block_user_failed_logins.png
docs/_static/change-password.png
docs/_static/login-two-factor-auth.png
docs/_static/native_auth_flow.png
docs/_static/signup-two-factor-auth.png
docs/_static/wrong_signup.png
jupyterhub_naasauthenticator.egg-info/PKG-INFO
jupyterhub_naasauthenticator.egg-info/SOURCES.txt
jupyterhub_naasauthenticator.egg-info/dependency_links.txt
jupyterhub_naasauthenticator.egg-info/requires.txt
jupyterhub_naasauthenticator.egg-info/top_level.txt
naasauthenticator/__init__.py
naasauthenticator/common-credentials.txt
naasauthenticator/handlers.py
naasauthenticator/naasauthenticator.py
naasauthenticator/orm.py
naasauthenticator/templates/admin.html
naasauthenticator/templates/autorization-area.html
naasauthenticator/templates/change-password.html
naasauthenticator/templates/home.html
naasauthenticator/templates/native-login.html
naasauthenticator/templates/not_running.html
naasauthenticator/templates/page.html
naasauthenticator/templates/reset-password.html
naasauthenticator/templates/spawn.html
naasauthenticator/templates/spawn_pending.html
naasauthenticator/templates/stop_pending.html
naasauthenticator/templates/token.html
naasauthenticator/tests/__init__.py
naasauthenticator/tests/test_authenticator.py
naasauthenticator/tests/test_orm.py