Metadata-Version: 2.1
Name: jupyterhub-naasauthenticator
Version: 0.7.1
Summary: JupyterHub Native Authenticator
Home-page: https://github.com/cashstory/naasauthenticator
Author: Martin DONADIEU
Author-email: bob@cashstory.com
License: 3 Clause BSD
Platform: UNKNOWN
Provides-Extra: dev
